README.md
setup.py
steganosort/__init__.py
steganosort/__main__.py
steganosort/cli.py
steganosort/steganosort.py
steganosort/util.py
steganosort.egg-info/PKG-INFO
steganosort.egg-info/SOURCES.txt
steganosort.egg-info/dependency_links.txt
steganosort.egg-info/entry_points.txt
steganosort.egg-info/requires.txt
steganosort.egg-info/top_level.txt