Metadata-Version: 2.1
Name: steganosort
Version: 0.1.0
Summary: Embed messages in the sort order of lists/dicts/JSON/tar.
Home-page: https://github.com/sz3/steganosort
Author: Stephen Zimmerman
Author-email: sz@recv.cc
License: GPLv3
Platform: UNKNOWN
Classifier: License :: OSI Approved :: GNU General Public License v3 (GPLv3)
Classifier: Programming Language :: Python :: 3
Classifier: Programming Language :: Python :: 3.6
Classifier: Programming Language :: Python :: 3.7
Classifier: Programming Language :: Python :: 3.8
Classifier: Programming Language :: Python :: 3.9
Classifier: Programming Language :: Python :: 3.10
Requires-Python: >=3.6
